mistsystems/__debug.py
mistsystems/__init__.py
mistsystems/__req.py
mistsystems/api.py
mistsystems/cli.py
mistsystems/models/__init__.py
mistsystems/models/privilege.py
mistsystems/models/wlan.py
mistsystems/models/orgs/__init__.py
mistsystems/models/orgs/sites.py
mistsystems/models/sites/__init__.py
mistsystems/models/sites/devices.py
mistsystems/models/sites/psks.py
mistsystems/models/sites/rogue.py
mistsystems/models/sites/settings.py
mistsystems/models/sites/webhooks.py
mistsystems/requests/__init__.py
mistsystems/requests/api_calls.py
mistsystems/requests/route.py
mistsystems/requests/orgs/__init__.py
mistsystems/requests/orgs/admins.py
mistsystems/requests/orgs/alarmtemplates.py
mistsystems/requests/orgs/assetfilters.py
mistsystems/requests/orgs/channels.py
mistsystems/requests/orgs/deviceprofiles.py
mistsystems/requests/orgs/info.py
mistsystems/requests/orgs/inventory.py
mistsystems/requests/orgs/licenses.py
mistsystems/requests/orgs/mxclusters.py
mistsystems/requests/orgs/mxedges.py
mistsystems/requests/orgs/mxtunnels.py
mistsystems/requests/orgs/networktemplates.py
mistsystems/requests/orgs/orgs.py
mistsystems/requests/orgs/psks.py
mistsystems/requests/orgs/rftemplates.py
mistsystems/requests/orgs/secpolicies.py
mistsystems/requests/orgs/settings.py
mistsystems/requests/orgs/sitegroups.py
mistsystems/requests/orgs/sites.py
mistsystems/requests/orgs/ssoroles.py
mistsystems/requests/orgs/ssos.py
mistsystems/requests/orgs/stats.py
mistsystems/requests/orgs/subscriptions.py
mistsystems/requests/orgs/templates.py
mistsystems/requests/orgs/webhooks.py
mistsystems/requests/orgs/wlans.py
mistsystems/requests/orgs/wxrules.py
mistsystems/requests/orgs/wxtags.py
mistsystems/requests/orgs/wxtunnels.py
mistsystems/requests/sites/__init__.py
mistsystems/requests/sites/assetfilters.py
mistsystems/requests/sites/assets.py
mistsystems/requests/sites/beacons.py
mistsystems/requests/sites/client_events.py
mistsystems/requests/sites/const.py
mistsystems.0.0.2-0.0.2.dist-info/LICENSE
mistsystems.0.0.2-0.0.2.dist-info/METADATA
mistsystems.0.0.2-0.0.2.dist-info/WHEEL
mistsystems.0.0.2-0.0.2.dist-info/top_level.txt
mistsystems.0.0.2-0.0.2.dist-info/RECORD
