Metadata-Version: 2.1
Name: mistsystems.0.0.2
Version: 0.0.2
Summary: Python Library to use Juniper-Mist APIs
Home-page: https://github.com/tmunzer/mistsystems
Author: Thomas Munzer
Author-email: tmunzer@juniper.net
License: UNKNOWN
Platform: UNKNOWN
Classifier: Programming Language :: Python :: 3
Classifier: License :: OSI Approved :: GNU General Public License v3 or later (GPLv3+)
Classifier: Operating System :: OS Independent
Requires-Python: >=3.6
